{"frames":{"general_00000":{"frame":{"x":1,"y":1,"w":8,"h":850},"sourceSize":{"w":8,"h":850}},"general_00001":{"frame":{"x":11,"y":1,"w":8,"h":850},"sourceSize":{"w":8,"h":850}},"general_00002":{"frame":{"x":21,"y":1,"w":8,"h":850},"sourceSize":{"w":8,"h":850}},"general_00003":{"frame":{"x":31,"y":1,"w":8,"h":850},"sourceSize":{"w":8,"h":850}},"general_00004":{"frame":{"x":41,"y":1,"w":8,"h":850},"sourceSize":{"w":8,"h":850}},"general_00005":{"frame":{"x":51,"y":1,"w":8,"h":850},"sourceSize":{"w":8,"h":850}},"general_00006":{"frame":{"x":61,"y":1,"w":8,"h":850},"sourceSize":{"w":8,"h":850}},"general_00007":{"frame":{"x":71,"y":1,"w":8,"h":850},"sourceSize":{"w":8,"h":850}},"general_00008":{"frame":{"x":81,"y":1,"w":8,"h":850},"sourceSize":{"w":8,"h":850}},"general_00009":{"frame":{"x":91,"y":1,"w":8,"h":850},"sourceSize":{"w":8,"h":850}},"general_00010":{"frame":{"x":101,"y":1,"w":8,"h":850},"sourceSize":{"w":8,"h":850}},"general_00011":{"frame":{"x":111,"y":1,"w":8,"h":850},"sourceSize":{"w":8,"h":850}},"general_00012":{"frame":{"x":121,"y":1,"w":8,"h":850},"sourceSize":{"w":8,"h":850}},"general_00013":{"frame":{"x":131,"y":1,"w":8,"h":850},"sourceSize":{"w":8,"h":850}},"general_00014":{"frame":{"x":141,"y":1,"w":8,"h":850},"sourceSize":{"w":8,"h":850}},"general_00015":{"frame":{"x":151,"y":1,"w":8,"h":850},"sourceSize":{"w":8,"h":850}},"general_00016":{"frame":{"x":161,"y":1,"w":8,"h":850},"sourceSize":{"w":8,"h":850}},"general_00017":{"frame":{"x":171,"y":1,"w":8,"h":850},"sourceSize":{"w":8,"h":850}},"general_00018":{"frame":{"x":181,"y":1,"w":8,"h":850},"sourceSize":{"w":8,"h":850}},"general_00019":{"frame":{"x":191,"y":1,"w":8,"h":850},"sourceSize":{"w":8,"h":850}},"general_00020":{"frame":{"x":201,"y":1,"w":8,"h":850},"sourceSize":{"w":8,"h":850}},"general_00021":{"frame":{"x":211,"y":1,"w":8,"h":850},"sourceSize":{"w":8,"h":850}},"general_00022":{"frame":{"x":221,"y":1,"w":8,"h":850},"sourceSize":{"w":8,"h":850}},"general_00023":{"frame":{"x":231,"y":1,"w":8,"h":850},"sourceSize":{"w":8,"h":850}},"general_00024":{"frame":{"x":241,"y":1,"w":8,"h":850},"sourceSize":{"w":8,"h":850}},"general_00025":{"frame":{"x":251,"y":1,"w":8,"h":850},"sourceSize":{"w":8,"h":850}},"general_00026":{"frame":{"x":261,"y":1,"w":8,"h":850},"sourceSize":{"w":8,"h":850}},"general_00027":{"frame":{"x":271,"y":1,"w":8,"h":850},"sourceSize":{"w":8,"h":850}},"general_00028":{"frame":{"x":281,"y":1,"w":8,"h":850},"sourceSize":{"w":8,"h":850}},"general_00029":{"frame":{"x":291,"y":1,"w":8,"h":850},"sourceSize":{"w":8,"h":850}},"general_00030":{"frame":{"x":301,"y":1,"w":8,"h":850},"sourceSize":{"w":8,"h":850}},"alltime_00000":{"frame":{"x":311,"y":1,"w":11,"h":850},"sourceSize":{"w":11,"h":850}},"alltime_00001":{"frame":{"x":324,"y":1,"w":11,"h":850},"sourceSize":{"w":11,"h":850}},"alltime_00002":{"frame":{"x":337,"y":1,"w":11,"h":850},"sourceSize":{"w":11,"h":850}},"alltime_00003":{"frame":{"x":350,"y":1,"w":11,"h":850},"sourceSize":{"w":11,"h":850}},"alltime_00004":{"frame":{"x":363,"y":1,"w":11,"h":850},"sourceSize":{"w":11,"h":850}},"alltime_00005":{"frame":{"x":376,"y":1,"w":11,"h":850},"sourceSize":{"w":11,"h":850}},"alltime_00006":{"frame":{"x":389,"y":1,"w":11,"h":850},"sourceSize":{"w":11,"h":850}},"alltime_00007":{"frame":{"x":402,"y":1,"w":11,"h":850},"sourceSize":{"w":11,"h":850}},"alltime_00008":{"frame":{"x":415,"y":1,"w":11,"h":850},"sourceSize":{"w":11,"h":850}},"alltime_00009":{"frame":{"x":428,"y":1,"w":11,"h":850},"sourceSize":{"w":11,"h":850}},"alltime_00010":{"frame":{"x":441,"y":1,"w":11,"h":850},"sourceSize":{"w":11,"h":850}},"alltime_00011":{"frame":{"x":454,"y":1,"w":11,"h":850},"sourceSize":{"w":11,"h":850}},"alltime_00012":{"frame":{"x":467,"y":1,"w":11,"h":850},"sourceSize":{"w":11,"h":850}},"alltime_00013":{"frame":{"x":480,"y":1,"w":11,"h":850},"sourceSize":{"w":11,"h":850}},"alltime_00014":{"frame":{"x":493,"y":1,"w":11,"h":850},"sourceSize":{"w":11,"h":850}},"alltime_00015":{"frame":{"x":506,"y":1,"w":11,"h":850},"sourceSize":{"w":11,"h":850}},"alltime_00016":{"frame":{"x":519,"y":1,"w":11,"h":850},"sourceSize":{"w":11,"h":850}},"alltime_00017":{"frame":{"x":532,"y":1,"w":11,"h":850},"sourceSize":{"w":11,"h":850}},"alltime_00018":{"frame":{"x":545,"y":1,"w":11,"h":850},"sourceSize":{"w":11,"h":850}},"alltime_00019":{"frame":{"x":558,"y":1,"w":11,"h":850},"sourceSize":{"w":11,"h":850}},"alltime_00020":{"frame":{"x":571,"y":1,"w":11,"h":850},"sourceSize":{"w":11,"h":850}},"alltime_00021":{"frame":{"x":584,"y":1,"w":11,"h":850},"sourceSize":{"w":11,"h":850}},"alltime_00022":{"frame":{"x":597,"y":1,"w":11,"h":850},"sourceSize":{"w":11,"h":850}},"alltime_00023":{"frame":{"x":610,"y":1,"w":11,"h":850},"sourceSize":{"w":11,"h":850}},"alltime_00024":{"frame":{"x":623,"y":1,"w":11,"h":850},"sourceSize":{"w":11,"h":850}},"alltime_00025":{"frame":{"x":636,"y":1,"w":11,"h":850},"sourceSize":{"w":11,"h":850}},"alltime_00026":{"frame":{"x":649,"y":1,"w":11,"h":850},"sourceSize":{"w":11,"h":850}},"alltime_00027":{"frame":{"x":662,"y":1,"w":11,"h":850},"sourceSize":{"w":11,"h":850}},"alltime_00028":{"frame":{"x":675,"y":1,"w":11,"h":850},"sourceSize":{"w":11,"h":850}},"alltime_00029":{"frame":{"x":688,"y":1,"w":11,"h":850},"sourceSize":{"w":11,"h":850}},"alltime_00030":{"frame":{"x":701,"y":1,"w":11,"h":850},"sourceSize":{"w":11,"h":850}}},"meta":{"app":"PixiAnimate","scale":1,"image":"res_BonusGame_atlas_1.png","size":{"w":1024,"h":1024}}}